[
    {
        "energy": -11.0,
        "num_occurrences": 705,
        "chain_break_fraction": 0.0
    },
    {
        "energy": -10.0,
        "num_occurrences": 18,
        "chain_break_fraction": 0.0
    },
    {
        "energy": -10.0,
        "num_occurrences": 10,
        "chain_break_fraction": 0.0
    },
    {
        "energy": -10.0,
        "num_occurrences": 23,
        "chain_break_fraction": 0.0
    },
    {
        "energy": -10.0,
        "num_occurrences": 1,
        "chain_break_fraction": 0.0
    },
    {
        "energy": -10.0,
        "num_occurrences": 2,
        "chain_break_fraction": 0.0
    },
    {
        "energy": -10.0,
        "num_occurrences": 13,
        "chain_break_fraction": 0.0
    },
    {
        "energy": -10.0,
        "num_occurrences": 6,
        "chain_break_fraction": 0.0
    },
    {
        "energy": -10.0,
        "num_occurrences": 2,
        "chain_break_fraction": 0.0
    },
    {
        "energy": -10.0,
        "num_occurrences": 2,
        "chain_break_fraction": 0.0
    },
    {
        "energy": -10.0,
        "num_occurrences": 2,
        "chain_break_fraction": 0.0
    },
    {
        "energy": -10.0,
        "num_occurrences": 18,
        "chain_break_fraction": 0.0
    },
    {
        "energy": -10.0,
        "num_occurrences": 1,
        "chain_break_fraction": 0.0
    },
    {
        "energy": -10.0,
        "num_occurrences": 1,
        "chain_break_fraction": 0.0
    },
    {
        "energy": -10.0,
        "num_occurrences": 16,
        "chain_break_fraction": 0.0
    },
    {
        "energy": -10.0,
        "num_occurrences": 13,
        "chain_break_fraction": 0.0
    },
    {
        "energy": -10.0,
        "num_occurrences": 18,
        "chain_break_fraction": 0.0
    },
    {
        "energy": -10.0,
        "num_occurrences": 32,
        "chain_break_fraction": 0.0
    },
    {
        "energy": -10.0,
        "num_occurrences": 12,
        "chain_break_fraction": 0.0
    },
    {
        "energy": -10.0,
        "num_occurrences": 25,
        "chain_break_fraction": 0.0
    },
    {
        "energy": -10.0,
        "num_occurrences": 25,
        "chain_break_fraction": 0.0
    },
    {
        "energy": -10.0,
        "num_occurrences": 1,
        "chain_break_fraction": 0.0
    },
    {
        "energy": -10.0,
        "num_occurrences": 27,
        "chain_break_fraction": 0.0
    },
    {
        "energy": -9.0,
        "num_occurrences": 3,
        "chain_break_fraction": 0.0
    },
    {
        "energy": -9.0,
        "num_occurrences": 1,
        "chain_break_fraction": 0.0
    },
    {
        "energy": -9.0,
        "num_occurrences": 1,
        "chain_break_fraction": 0.0
    },
    {
        "energy": -9.0,
        "num_occurrences": 1,
        "chain_break_fraction": 0.0
    },
    {
        "energy": -9.0,
        "num_occurrences": 1,
        "chain_break_fraction": 0.0
    },
    {
        "energy": -9.0,
        "num_occurrences": 1,
        "chain_break_fraction": 0.0
    },
    {
        "energy": -9.0,
        "num_occurrences": 2,
        "chain_break_fraction": 0.0
    },
    {
        "energy": -9.0,
        "num_occurrences": 1,
        "chain_break_fraction": 0.0
    },
    {
        "energy": -9.0,
        "num_occurrences": 1,
        "chain_break_fraction": 0.0
    },
    {
        "energy": -9.0,
        "num_occurrences": 1,
        "chain_break_fraction": 0.0
    },
    {
        "energy": -9.0,
        "num_occurrences": 1,
        "chain_break_fraction": 0.0
    },
    {
        "energy": -9.0,
        "num_occurrences": 1,
        "chain_break_fraction": 0.0
    },
    {
        "energy": -9.0,
        "num_occurrences": 1,
        "chain_break_fraction": 0.0
    },
    {
        "energy": -9.0,
        "num_occurrences": 1,
        "chain_break_fraction": 0.0
    },
    {
        "energy": -9.0,
        "num_occurrences": 1,
        "chain_break_fraction": 0.0
    },
    {
        "energy": -9.0,
        "num_occurrences": 2,
        "chain_break_fraction": 0.0
    },
    {
        "energy": -9.0,
        "num_occurrences": 2,
        "chain_break_fraction": 0.0
    },
    {
        "energy": -9.0,
        "num_occurrences": 1,
        "chain_break_fraction": 0.0
    },
    {
        "energy": -8.0,
        "num_occurrences": 1,
        "chain_break_fraction": 0.04
    },
    {
        "energy": -8.0,
        "num_occurrences": 1,
        "chain_break_fraction": 0.0
    },
    {
        "energy": -8.0,
        "num_occurrences": 1,
        "chain_break_fraction": 0.0
    },
    {
        "energy": -7.0,
        "num_occurrences": 1,
        "chain_break_fraction": 0.0
    },
    {
        "Gamma": 2.0,
        "Annealing_time": 50,
        "So dinh": 25,
        "So canh": 60,
        "Mat do do thi": 0.2,
        "Nang luong thap nhat bi sai ban dau": -11.0,
        "So lan vi pham rang buoc": 3,
        "So solution dung la": 705,
        "Phan tram so cau tra loi dung": 0.705,
        "Best solutions of samples %": "0.1",
        "Thoi gian chay": {
            "qpu_sampling_time": 113040.0,
            "qpu_anneal_time_per_sample": 20.0,
            "qpu_readout_time_per_sample": 72.46,
            "qpu_access_time": 128801.56,
            "qpu_access_overhead_time": 1222.44,
            "qpu_programming_time": 15761.56,
            "qpu_delay_time_per_sample": 20.58,
            "post_processing_overhead_time": 1.0,
            "total_post_processing_time": 1.0
        },
        "Nang luong thap nhat va cac loi giai toi uu theo ortools": 11
    }
]