[
    {
        "energy": -10.0,
        "num_occurrences": 833,
        "chain_break_fraction": 0.0
    },
    {
        "energy": -9.0,
        "num_occurrences": 1,
        "chain_break_fraction": 0.0
    },
    {
        "energy": -9.0,
        "num_occurrences": 3,
        "chain_break_fraction": 0.0
    },
    {
        "energy": -9.0,
        "num_occurrences": 7,
        "chain_break_fraction": 0.0
    },
    {
        "energy": -9.0,
        "num_occurrences": 3,
        "chain_break_fraction": 0.0
    },
    {
        "energy": -9.0,
        "num_occurrences": 5,
        "chain_break_fraction": 0.0
    },
    {
        "energy": -9.0,
        "num_occurrences": 3,
        "chain_break_fraction": 0.0
    },
    {
        "energy": -9.0,
        "num_occurrences": 12,
        "chain_break_fraction": 0.0
    },
    {
        "energy": -9.0,
        "num_occurrences": 4,
        "chain_break_fraction": 0.0
    },
    {
        "energy": -9.0,
        "num_occurrences": 3,
        "chain_break_fraction": 0.0
    },
    {
        "energy": -9.0,
        "num_occurrences": 6,
        "chain_break_fraction": 0.0
    },
    {
        "energy": -9.0,
        "num_occurrences": 5,
        "chain_break_fraction": 0.0
    },
    {
        "energy": -9.0,
        "num_occurrences": 8,
        "chain_break_fraction": 0.0
    },
    {
        "energy": -9.0,
        "num_occurrences": 1,
        "chain_break_fraction": 0.0
    },
    {
        "energy": -9.0,
        "num_occurrences": 4,
        "chain_break_fraction": 0.0
    },
    {
        "energy": -9.0,
        "num_occurrences": 6,
        "chain_break_fraction": 0.0
    },
    {
        "energy": -9.0,
        "num_occurrences": 1,
        "chain_break_fraction": 0.0
    },
    {
        "energy": -9.0,
        "num_occurrences": 1,
        "chain_break_fraction": 0.0
    },
    {
        "energy": -9.0,
        "num_occurrences": 16,
        "chain_break_fraction": 0.0
    },
    {
        "energy": -9.0,
        "num_occurrences": 11,
        "chain_break_fraction": 0.0
    },
    {
        "energy": -9.0,
        "num_occurrences": 9,
        "chain_break_fraction": 0.0
    },
    {
        "energy": -9.0,
        "num_occurrences": 7,
        "chain_break_fraction": 0.0
    },
    {
        "energy": -9.0,
        "num_occurrences": 3,
        "chain_break_fraction": 0.0
    },
    {
        "energy": -9.0,
        "num_occurrences": 1,
        "chain_break_fraction": 0.0
    },
    {
        "energy": -9.0,
        "num_occurrences": 3,
        "chain_break_fraction": 0.0
    },
    {
        "energy": -9.0,
        "num_occurrences": 1,
        "chain_break_fraction": 0.0
    },
    {
        "energy": -9.0,
        "num_occurrences": 1,
        "chain_break_fraction": 0.0
    },
    {
        "energy": -9.0,
        "num_occurrences": 1,
        "chain_break_fraction": 0.0
    },
    {
        "energy": -9.0,
        "num_occurrences": 1,
        "chain_break_fraction": 0.0
    },
    {
        "energy": -9.0,
        "num_occurrences": 1,
        "chain_break_fraction": 0.0
    },
    {
        "energy": -9.0,
        "num_occurrences": 1,
        "chain_break_fraction": 0.0
    },
    {
        "energy": -9.0,
        "num_occurrences": 2,
        "chain_break_fraction": 0.0
    },
    {
        "energy": -9.0,
        "num_occurrences": 2,
        "chain_break_fraction": 0.0
    },
    {
        "energy": -9.0,
        "num_occurrences": 3,
        "chain_break_fraction": 0.0
    },
    {
        "energy": -9.0,
        "num_occurrences": 1,
        "chain_break_fraction": 0.0
    },
    {
        "energy": -9.0,
        "num_occurrences": 6,
        "chain_break_fraction": 0.0
    },
    {
        "energy": -9.0,
        "num_occurrences": 2,
        "chain_break_fraction": 0.0
    },
    {
        "energy": -9.0,
        "num_occurrences": 10,
        "chain_break_fraction": 0.0
    },
    {
        "energy": -9.0,
        "num_occurrences": 1,
        "chain_break_fraction": 0.0
    },
    {
        "energy": -9.0,
        "num_occurrences": 4,
        "chain_break_fraction": 0.0
    },
    {
        "energy": -9.0,
        "num_occurrences": 3,
        "chain_break_fraction": 0.0
    },
    {
        "energy": -9.0,
        "num_occurrences": 1,
        "chain_break_fraction": 0.0
    },
    {
        "energy": -9.0,
        "num_occurrences": 1,
        "chain_break_fraction": 0.0
    },
    {
        "energy": -8.0,
        "num_occurrences": 1,
        "chain_break_fraction": 0.0
    },
    {
        "energy": -8.0,
        "num_occurrences": 1,
        "chain_break_fraction": 0.0
    },
    {
        "Gamma": 2.0,
        "Annealing_time": 10,
        "So dinh": 19,
        "So canh": 18,
        "Mat do do thi": 0.10526315789473684,
        "Nang luong thap nhat": -10.0,
        "So lan vi pham rang buoc": 0,
        "So solution dung la": 833,
        "Phan tram so cau tra loi dung": 0.833,
        "Best solutions of samples %": "0.1",
        "Thoi gian chay": {
            "qpu_sampling_time": 111560.0,
            "qpu_anneal_time_per_sample": 20.0,
            "qpu_readout_time_per_sample": 70.98,
            "qpu_access_time": 127320.36,
            "qpu_access_overhead_time": 1472.64,
            "qpu_programming_time": 15760.36,
            "qpu_delay_time_per_sample": 20.58,
            "post_processing_overhead_time": 1.0,
            "total_post_processing_time": 1.0
        }
    }
]